force_backup_automator/BackupController.py
force_backup_automator/__init__.py
force_backup_automator-1.4.dist-info/METADATA
force_backup_automator-1.4.dist-info/WHEEL
force_backup_automator-1.4.dist-info/top_level.txt
force_backup_automator-1.4.dist-info/RECORD
